Workbook

Sheet Summary Dashboard
A1: PhonePe Transaction Summary Dashboard
A3: Total Transactions | B3: =COUNTA('All Transactions'!E:E)-1 -> 1930
A4: Total Debits (Spends) | B4: =SUMIF('All Transactions'!G:G,"DEBIT",'All Transactions'!H:H) -> 979706.5
A5: Total Credits (Income) | B5: =SUMIF('All Transactions'!G:G,"CREDIT",'All Transactions'!H:H) -> 645469.9
A6: Net Cash Flow | B6: =B5-B4 -> -334236.6
A9: Top 10 Highest Debit Transactions
A10: Date | B10: Details | C10: Amount (INR)
A11: Jun 07, 2025 | B11: Transfer to XXXX7370 | C11: 31400
A12: Feb 08, 2026 | B12: Paid to Abhi 💗 | C12: 30000
A13: Jun 07, 2025 | B13: Transfer to XXXXXX6646 | C13: 27900
A14: Jul 30, 2025 | B14: Paid to Kotak Mahindra Bank Ltd | C14: 25000
A15: Jul 15, 2025 | B15: Transfer to XXXX7370 | C15: 25000
A16: Jun 25, 2025 | B16: Paid to QSPIDERSUTEST YANTRA SW SOLIP LTD AIR1QlQW0jHkKpWos6T5769134280QPAY02 | C16: 21000
A17: Aug 25, 2025 | B17: Transfer to XXXXXXXX1137 | C17: 20000
A18: Aug 25, 2025 | B18: Transfer to XXXX7370 | C18: 20000
A19: Aug 25, 2025 | B19: Transfer to XXXXXXXX1137 | C19: 18000
A20: Aug 25, 2025 | B20: Transfer to XXXXXX6646 | C20: 18000

Sheet All Transactions
A1: day | B1: month2 | C1: month | D1: year | E1: Date | F1: Time | G1: Type | H1: Amount (INR) | I1: Details | J1: Transaction ID | K1: UTR No. | L1: Account Info | M1: days | N1: date2
A2: =MID(E2,5,2) -> 04 | B2: =_xlfn.SWITCH(Table4[[#This Row],[month]],"jan",1,"feb",2,"mar",3,"apr",4,"may",5,"jun",6,"jul",7,"aug",8,"sep",9,"oct",10,"nov",11,"dec",12,"no month") -> 6 | C2: =LEFT('All Transactions'!$E2,3) -> Jun | D2: =RIGHT(E2,4) -> 2026 | E2: Jun 04, 2026 | F2: 10:11 am | G2: DEBIT | H2: 27 | I2: Paid to Kodithyala Tejasvi | J2: T2606041011314875701288 | K2: 045220263536 | L2: Paid by XXXXXXXX1137 | M2: =TEXT(A2,"dddd") -> Wednesday | N2: =DATE(Table4[[#This Row],[year]],Table4[[#This Row],[month2]],Table4[[#This Row],[day]]) -> 46177
A3: =MID(E3,5,2) -> 04 | B3: =_xlfn.SWITCH(Table4[[#This Row],[month]],"jan",1,"feb",2,"mar",3,"apr",4,"may",5,"jun",6,"jul",7,"aug",8,"sep",9,"oct",10,"nov",11,"dec",12,"no month") -> 6 | C3: =LEFT('All Transactions'!$E3,3) -> Jun | D3: =RIGHT(E3,4) -> 2026 | E3: Jun 04, 2026 | F3: 10:10 am | G3: DEBIT | H3: 10 | I3: Paid to Kodithyala Tejasvi | J3: T2606041010294837143118 | K3: 464727463411 | L3: Paid by XXXXXXXX1137 | M3: =TEXT(A3,"dddd") -> Wednesday | N3: =DATE(Table4[[#This Row],[year]],Table4[[#This Row],[month2]],Table4[[#This Row],[day]]) -> 46177
A4: =MID(E4,5,2) -> 04 | B4: =_xlfn.SWITCH(Table4[[#This Row],[month]],"jan",1,"feb",2,"mar",3,"apr",4,"may",5,"jun",6,"jul",7,"aug",8,"sep",9,"oct",10,"nov",11,"dec",12,"no month") -> 6 | C4: =LEFT('All Transactions'!$E4,3) -> Jun | D4: =RIGHT(E4,4) -> 2026 | E4: Jun 04, 2026 | F4: 10:08 am | G4: DEBIT | H4: 70 | I4: Paid to GANGARABOINA MADHUKA | J4: T2606041008374360542582 | K4: 062979462011 | L4: Paid by XXXXXXXX1137 | M4: =TEXT(A4,"dddd") -> Wednesday | N4: =DATE(Table4[[#This Row],[year]],Table4[[#This Row],[month2]],Table4[[#This Row],[day]]) -> 46177
A5: =MID(E5,5,2) -> 04 | B5: =_xlfn.SWITCH(Table4[[#This Row],[month]],"jan",1,"feb",2,"mar",3,"apr",4,"may",5,"jun",6,"jul",7,"aug",8,"sep",9,"oct",10,"nov",11,"dec",12,"no month") -> 6 | C5: =LEFT('All Transactions'!$E5,3) -> Jun | D5: =RIGHT(E5,4) -> 2026 | E5: Jun 04, 2026 | F5: 09:09 am | G5: DEBIT | H5: 20 | I5: Paid to JUNNU TEA POINT | J5: T2606040909435947046539 | K5: 141109617820 | L5: Paid by XXXXXXXX1137 | M5: =TEXT(A5,"dddd") -> Wednesday | N5: =DATE(Table4[[#This Row],[year]],Table4[[#This Row],[month2]],Table4[[#This Row],[day]]) -> 46177
A6: =MID(E6,5,2) -> 04 | B6: =_xlfn.SWITCH(Table4[[#This Row],[month]],"jan",1,"feb",2,"mar",3,"apr",4,"may",5,"jun",6,"jul",7,"aug",8,"sep",9,"oct",10,"nov",11,"dec",12,"no month") -> 6 | C6: =LEFT('All Transactions'!$E6,3) -> Jun | D6: =RIGHT(E6,4) -> 2026 | E6: Jun 04, 2026 | F6: 08:29 am | G6: DEBIT | H6: 673 | I6: Transfer to XXXXXXXX1137 | J6: T2606040829273598415025 | K6: 684310994967 | L6: Paid by XXXX7370 | M6: =TEXT(A6,"dddd") -> Wednesday | N6: =DATE(Table4[[#This Row],[year]],Table4[[#This Row],[month2]],Table4[[#This Row],[day]]) -> 46177
A7: =MID(E7,5,2) -> 04 | B7: =_xlfn.SWITCH(Table4[[#This Row],[month]],"jan",1,"feb",2,"mar",3,"apr",4,"may",5,"jun",6,"jul",7,"aug",8,"sep",9,"oct",10,"nov",11,"dec",12,"no month") -> 6 | C7: =LEFT('All Transactions'!$E7,3) -> Jun | D7: =RIGHT(E7,4) -> 2026 | E7: Jun 04, 2026 | F7: 06:00 am | G7: DEBIT | H7: 673 | I7: Payment to RentomojoPvtLtd | J7: OLEX2606040600103873282437 | K7: 615506335127 | L7: Paid by XXXXXXXX1137 | M7: =TEXT(A7,"dddd") -> Wednesday | N7: =DATE(Table4[[#This Row],[year]],Table4[[#This Row],[month2]],Table4[[#This Row],[day]]) -> 46177
A8: =MID(E8,5,2) -> 03 | B8: =_xlfn.SWITCH(Table4[[#This Row],[month]],"jan",1,"feb",2,"mar",3,"apr",4,"may",5,"jun",6,"jul",7,"aug",8,"sep",9,"oct",10,"nov",11,"dec",12,"no month") -> 6 | C8: =LEFT('All Transactions'!$E8,3) -> Jun | D8: =RIGHT(E8,4) -> 2026 | E8: Jun 03, 2026 | F8: 09:07 pm | G8: CREDIT | H8: 17 | I8: Received from phani | J8: T2606032107243476749558 | K8: 336002225185 | L8: Credited to XXXXXXXX1137 | M8: =TEXT(A8,"dddd") -> Tuesday | N8: =DATE(Table4[[#This Row],[year]],Table4[[#This Row],[month2]],Table4[[#This Row],[day]]) -> 46176
A9: =MID(E9,5,2) -> 03 | B9: =_xlfn.SWITCH(Table4[[#This Row],[month]],"jan",1,"feb",2,"mar",3,"apr",4,"may",5,"jun",6,"jul",7,"aug",8,"sep",9,"oct",10,"nov",11,"dec",12,"no month") -> 6 | C9: =LEFT('All Transactions'!$E9,3) -> Jun | D9: =RIGHT(E9,4) -> 2026 | E9: Jun 03, 2026 | F9: 08:47 pm | G9: CREDIT | H9: 76 | I9: Received from BACHU SHIVA SHANKAR | J9: T2606032047526816822372 | K9: 652044153724 | L9: Credited to XXXXXXXX1137 | M9: =TEXT(A9,"dddd") -> Tuesday | N9: =DATE(Table4[[#This Row],[year]],Table4[[#This Row],[month2]],Table4[[#This Row],[day]]) -> 46176
A10: =MID(E10,5,2) -> 03 | B10: =_xlfn.SWITCH(Table4[[#This Row],[month]],"jan",1,"feb",2,"mar",3,"apr",4,"may",5,"jun",6,"jul",7,"aug",8,"sep",9,"oct",10,"nov",11,"dec",12,"no month") -> 6 | C10: =LEFT('All Transactions'!$E10,3) -> Jun | D10: =RIGHT(E10,4) -> 2026 | E10: Jun 03, 2026 | F10: 06:25 pm | G10: DEBIT | H10: 40 | I10: Paid to GANGARABOINA MADHUKA | J10: T2606031825293685051886 | K10: 789171415403 | L10: Paid by XXXXXXXX1137 | M10: =TEXT(A10,"dddd") -> Tuesday | N10: =DATE(Table4[[#This Row],[year]],Table4[[#This Row],[month2]],Table4[[#This Row],[day]]) -> 46176
A11: =MID(E11,5,2) -> 03 | B11: =_xlfn.SWITCH(Table4[[#This Row],[month]],"jan",1,"feb",2,"mar",3,"apr",4,"may",5,"jun",6,"jul",7,"aug",8,"sep",9,"oct",10,"nov",11,"dec",12,"no month") -> 6 | C11: =LEFT('All Transactions'!$E11,3) -> Jun | D11: =RIGHT(E11,4) -> 2026 | E11: Jun 03, 2026 | F11: 02:51 pm | G11: DEBIT | H11: 10 | I11: Paid to Kodithyala Tejasvi | J11: T2606031451095158039712 | K11: 673509106980 | L11: Paid by XXXXXXXX1137 | M11: =TEXT(A11,"dddd") -> Tuesday | N11: =DATE(Table4[[#This Row],[year]],Table4[[#This Row],[month2]],Table4[[#This Row],[day]]) -> 46176
A12: =MID(E12,5,2) -> 03 | B12: =_xlfn.SWITCH(Table4[[#This Row],[month]],"jan",1,"feb",2,"mar",3,"apr",4,"may",5,"jun",6,"jul",7,"aug",8,"sep",9,"oct",10,"nov",11,"dec",12,"no month") -> 6 | C12: =LEFT('All Transactions'!$E12,3) -> Jun | D12: =RIGHT(E12,4) -> 2026 | E12: Jun 03, 2026 | F12: 02:48 pm | G12: DEBIT | H12: 75 | I12: Paid to B22_YOUSUFGUDA_2 | J12: T2606031448258520977879 | K12: 227595184341 | L12: Paid by XXXX7370 | M12: =TEXT(A12,"dddd") -> Tuesday | N12: =DATE(Table4[[#This Row],[year]],Table4[[#This Row],[month2]],Table4[[#This Row],[day]]) -> 46176
A13: =MID(E13,5,2) -> 03 | B13: =_xlfn.SWITCH(Table4[[#This Row],[month]],"jan",1,"feb",2,"mar",3,"apr",4,"may",5,"jun",6,"jul",7,"aug",8,"sep",9,"oct",10,"nov",11,"dec",12,"no month") -> 6 | C13: =LEFT('All Transactions'!$E13,3) -> Jun | D13: =RIGHT(E13,4) -> 2026 | E13: Jun 03, 2026 | F13: 02:33 pm | G13: DEBIT | H13: 5 | I13: Paid to Kodithyala Tejasvi | J13: T2606031433292725176840 | K13: 378486486222 | L13: Paid by XXXXXXXX1137 | M13: =TEXT(A13,"dddd") -> Tuesday | N13: =DATE(Table4[[#This Row],[year]],Table4[[#This Row],[month2]],Table4[[#This Row],[day]]) -> 46176
... A747: =MID(E747,5,2) -> 12 | B747: =_xlfn.SWITCH(Table4[[#This Row],[month]],"jan",1,"feb",2,"mar",3,"apr",4,"may",5,"jun",6,"jul",7,"aug",8,"sep",9,"oct",10,"nov",11,"dec",12,"no month") -> 3 | C747: =LEFT('All Transactions'!$E747,3) -> Mar | D747: =RIGHT(E747,4) -> 2026 | E747: Mar 12, 2026 | F747: 11:16 am | G747: CREDIT | H747: 60 | I747: Received from Manikanta | J747: T2603121116444633084840 | K747: 962112293900 | L747: Credited to XXXXXXXX1137 | M747: =TEXT(A747,"dddd") -> Thursday | N747: =DATE(Table4[[#This Row],[year]],Table4[[#This Row],[month2]],Table4[[#This Row],[day]]) -> 46093
A748: =MID(E748,5,2) -> 12 | B748: =_xlfn.SWITCH(Table4[[#This Row],[month]],"jan",1,"feb",2,"mar",3,"apr",4,"may",5,"jun",6,"jul",7,"aug",8,"sep",9,"oct",10,"nov",11,"dec",12,"no month") -> 3 | C748: =LEFT('All Transactions'!$E748,3) -> Mar | D748: =RIGHT(E748,4) -> 2026 | E748: Mar 12, 2026 | F748: 10:18 am | G748: DEBIT | H748: 3661.8 | I748: Paid to Narsimha Reddy Engineering College PTM60312802827912628241202603121018 | K748: 201755603751 | L748: Paid by XXXXXXXX1137 | M748: =TEXT(A748,"dddd") -> Thursday | N748: =DATE(Table4[[#This Row],[year]],Table4[[#This Row],[month2]],Table4[[#This Row],[day]]) -> 46093
A749: =MID(E749,5,2) -> 12 | B749: =_xlfn.SWITCH(Table4[[#This Row],[month]],"jan",1,"feb",2,"mar",3,"apr",4,"may",5,"jun",6,"jul",7,"aug",8,"sep",9,"oct",10,"nov",11,"dec",12,"no month") -> 3 | C749: =LEFT('All Transactions'!$E749,3) -> Mar | D749: =RIGHT(E749,4) -> 2026 | E749: Mar 12, 2026 | F749: 10:12 am | G749: CREDIT | H749: 4000 | I749: Received from Babai | J749: T2603121012418335324743 | K749: 528910406974 | L749: Credited to XXXXXXXX1137 | M749: =TEXT(A749,"dddd") -> Thursday | N749: =DATE(Table4[[#This Row],[year]],Table4[[#This Row],[month2]],Table4[[#This Row],[day]]) -> 46093
A750: =MID(E750,5,2) -> 11 | B750: =_xlfn.SWITCH(Table4[[#This Row],[month]],"jan",1,"feb",2,"mar",3,"apr",4,"may",5,"jun",6,"jul",7,"aug",8,"sep",9,"oct",10,"nov",11,"dec",12,"no month") -> 3 | C750: =LEFT('All Transactions'!$E750,3) -> Mar | D750: =RIGHT(E750,4) -> 2026 | E750: Mar 11, 2026 | F750: 09:11 pm | G750: DEBIT | H750: 10 | I750: Paid to Shivaparvathi kirana general merchant | J750: T2603112111282360388611 | K750: 707452042790 | L750: Paid by XXXXXXXX1137 | M750: =TEXT(A750,"dddd") -> Wednesday | N750: =DATE(Table4[[#This Row],[year]],Table4[[#This Row],[month2]],Table4[[#This Row],[day]]) -> 46092
A751: =MID(E751,5,2) -> 11 | B751: =_xlfn.SWITCH(Table4[[#This Row],[month]],"jan",1,"feb",2,"mar",3,"apr",4,"may",5,"jun",6,"jul",7,"aug",8,"sep",9,"oct",10,"nov",11,"dec",12,"no month") -> 3 | C751: =LEFT('All Transactions'!$E751,3) -> Mar | D751: =RIGHT(E751,4) -> 2026 | E751: Mar 11, 2026 | F751: 09:10 pm | G751: DEBIT | H751: 30 | I751: Paid to Shaheen Chicken Maarket | J751: T2603112110316806416658 | K751: 294846718737 | L751: Paid by XXXXXXXX1137 | M751: =TEXT(A751,"dddd") -> Wednesday | N751: =DATE(Table4[[#This Row],[year]],Table4[[#This Row],[month2]],Table4[[#This Row],[day]]) -> 46092
A752: =MID(E752,5,2) -> 11 | B752: =_xlfn.SWITCH(Table4[[#This Row],[month]],"jan",1,"feb",2,"mar",3,"apr",4,"may",5,"jun",6,"jul",7,"aug",8,"sep",9,"oct",10,"nov",11,"dec",12,"no month") -> 3 | C752: =LEFT('All Transactions'!$E752,3) -> Mar | D752: =RIGHT(E752,4) -> 2026 | E752: Mar 11, 2026 | F752: 11:16 am | G752: DEBIT | H752: 60 | I752: Paid to Manikanta | J752: T2603111116011860852908 | K752: 964483539313 | L752: Paid by XXXXXXXX1137 | M752: =TEXT(A752,"dddd") -> Wednesday | N752: =DATE(Table4[[#This Row],[year]],Table4[[#This Row],[month2]],Table4[[#This Row],[day]]) -> 46092
A753: =MID(E753,5,2) -> 10 | B753: =_xlfn.SWITCH(Table4[[#This Row],[month]],"jan",1,"feb",2,"mar",3,"apr",4,"may",5,"jun",6,"jul",7,"aug",8,"sep",9,"oct",10,"nov",11,"dec",12,"no month") -> 3 | C753: =LEFT('All Transactions'!$E753,3) -> Mar | D753: =RIGHT(E753,4) -> 2026 | E753: Mar 10, 2026 | F753: 10:12 am | G753: DEBIT | H753: 40 | I753: Paid to Mahalakshmi Vegetables | J753: T2603101012092977634860 | K753: 187390887701 | L753: Paid by XXXXXXXX1137 | M753: =TEXT(A753,"dddd") -> Tuesday | N753: =DATE(Table4[[#This Row],[year]],Table4[[#This Row],[month2]],Table4[[#This Row],[day]]) -> 46091
A754: =MID(E754,5,2) -> 09 | B754: =_xlfn.SWITCH(Table4[[#This Row],[month]],"jan",1,"feb",2,"mar",3,"apr",4,"may",5,"jun",6,"jul",7,"aug",8,"sep",9,"oct",10,"nov",11,"dec",12,"no month") -> 3 | C754: =LEFT('All Transactions'!$E754,3) -> Mar | D754: =RIGHT(E754,4) -> 2026 | E754: Mar 09, 2026 | F754: 11:24 pm | G754: DEBIT | H754: 40 | I754: Paid to Charan 💗 | J754: T2603092324265952066037 | K754: 920583072131 | L754: Paid by XXXXXXXX1137 | M754: =TEXT(A754,"dddd") -> Monday | N754: =DATE(Table4[[#This Row],[year]],Table4[[#This Row],[month2]],Table4[[#This Row],[day]]) -> 46090
A755: =MID(E755,5,2) -> 09 | B755: =_xlfn.SWITCH(Table4[[#This Row],[month]],"jan",1,"feb",2,"mar",3,"apr",4,"may",5,"jun",6,"jul",7,"aug",8,"sep",9,"oct",10,"nov",11,"dec",12,"no month") -> 3 | C755: =LEFT('All Transactions'!$E755,3) -> Mar | D755: =RIGHT(E755,4) -> 2026 | E755: Mar 09, 2026 | F755: 11:23 pm | G755: DEBIT | H755: 147 | I755: Paid to SWIGGY | J755: T2603092323316432677117 | K755: 747326013752 | L755: Paid by XXXXXXXX1137 | M755: =TEXT(A755,"dddd") -> Monday | N755: =DATE(Table4[[#This Row],[year]],Table4[[#This Row],[month2]],Table4[[#This Row],[day]]) -> 46090
A756: =MID(E756,5,2) -> 09 | B756: =_xlfn.SWITCH(Table4[[#This Row],[month]],"jan",1,"feb",2,"mar",3,"apr",4,"may",5,"jun",6,"jul",7,"aug",8,"sep",9,"oct",10,"nov",11,"dec",12,"no month") -> 3 | C756: =LEFT('All Transactions'!$E756,3) -> Mar | D756: =RIGHT(E756,4) -> 2026 | E756: Mar 09, 2026 | F756: 07:36 pm | G756: CREDIT | H756: 250 | I756: Received from Charan 💗 | J756: T2603091936573672532277 | K756: 116822460073 | L756: Credited to XXXXXXXX1137 | M756: =TEXT(A756,"dddd") -> Monday | N756: =DATE(Table4[[#This Row],[year]],Table4[[#This Row],[month2]],Table4[[#This Row],[day]]) -> 46090
A757: =MID(E757,5,2) -> 09 | B757: =_xlfn.SWITCH(Table4[[#This Row],[month]],"jan",1,"feb",2,"mar",3,"apr",4,"may",5,"jun",6,"jul",7,"aug",8,"sep",9,"oct",10,"nov",11,"dec",12,"no month") -> 3 | C757: =LEFT('All Transactions'!$E757,3) -> Mar | D757: =RIGHT(E757,4) -> 2026 | E757: Mar 09, 2026 | F757: 06:42 pm | G757: DEBIT | H757: 300 | I757: Paid to RAJAMMA VEMULA | J757: T2603091842370219580366 | K757: 449355061023 | L757: Paid by XXXXXXXX1137 | M757: =TEXT(A757,"dddd") -> Monday | N757: =DATE(Table4[[#This Row],[year]],Table4[[#This Row],[month2]],Table4[[#This Row],[day]]) -> 46090
A758: =MID(E758,5,2) -> 09 | B758: =_xlfn.SWITCH(Table4[[#This Row],[month]],"jan",1,"feb",2,"mar",3,"apr",4,"may",5,"jun",6,"jul",7,"aug",8,"sep",9,"oct",10,"nov",11,"dec",12,"no month") -> 3 | C758: =LEFT('All Transactions'!$E758,3) -> Mar | D758: =RIGHT(E758,4) -> 2026 | E758: Mar 09, 2026 | F758: 06:41 pm | G758: CREDIT | H758: 800 | I758: Received from Manikanta | J758: T2603091841428477592855 | K758: 079020923038 | L758: Credited to XXXXXXXX1137 | M758: =TEXT(A758,"dddd") -> Monday | N758: =DATE(Table4[[#This Row],[year]],Table4[[#This Row],[month2]],Table4[[#This Row],[day]]) -> 46090
A759: =MID(E759,5,2) -> 09 | B759: =_xlfn.SWITCH(Table4[[#This Row],[month]],"jan",1,"feb",2,"mar",3,"apr",4,"may",5,"jun",6,"jul",7,"aug",8,"sep",9,"oct",10,"nov",11,"dec",12,"no month") -> 3 | C759: =LEFT('All Transactions'!$E759,3) -> Mar | D759: =RIGHT(E759,4) -> 2026 | E759: Mar 09, 2026 | F759: 10:02 am | G759: DEBIT | H759: 70 | I759: Paid to Sri Durga bhavani reddy tiffin centre | J759: T2603091002384717451639 | K759: 129561376004 | L759: Paid by XXXXXXXX1137 | M759: =TEXT(A759,"dddd") -> Monday | N759: =DATE(Table4[[#This Row],[year]],Table4[[#This Row],[month2]],Table4[[#This Row],[day]]) -> 46090
A760: =MID(E760,5,2) -> 08 | B760: =_xlfn.SWITCH(Table4[[#This Row],[month]],"jan",1,"feb",2,"mar",3,"apr",4,"may",5,"jun",6,"jul",7,"aug",8,"sep",9,"oct",10,"nov",11,"dec",12,"no month") -> 3 | C760: =LEFT('All Transactions'!$E760,3) -> Mar | D760: =RIGHT(E760,4) -> 2026 | E760: Mar 08, 2026 | F760: 11:10 pm | G760: DEBIT | H760: 100 | I760: Paid to Jatprole Filling Station | J760: T2603082310233826218924 | K760: 903788678537 | L760: Paid by XXXXXXXX1137 | M760: =TEXT(A760,"dddd") -> Sunday | N760: =DATE(Table4[[#This Row],[year]],Table4[[#This Row],[month2]],Table4[[#This Row],[day]]) -> 46089
... A856: =MID(E856,5,2) -> 24 | B856: =_xlfn.SWITCH(Table4[[#This Row],[month]],"jan",1,"feb",2,"mar",3,"apr",4,"may",5,"jun",6,"jul",7,"aug",8,"sep",9,"oct",10,"nov",11,"dec",12,"no month") -> 2 | C856: =LEFT('All Transactions'!$E856,3) -> Feb | D856: =RIGHT(E856,4) -> 2026 | E856: Feb 24, 2026 | F856: 06:19 pm | G856: DEBIT | H856: 10 | I856: Paid to Sri Sai super cool drink 2 ₹ 1 Gift Card ₹ 9 | J856: T2602241819381978058161 | K856: 486325389493 | L856: Paid by XXXXXXXX1137 | M856: =TEXT(A856,"dddd") -> Tuesday | N856: =DATE(Table4[[#This Row],[year]],Table4[[#This Row],[month2]],Table4[[#This Row],[day]]) -> 46077
A857: =MID(E857,5,2) -> 24 | B857: =_xlfn.SWITCH(Table4[[#This Row],[month]],"jan",1,"feb",2,"mar",3,"apr",4,"may",5,"jun",6,"jul",7,"aug",8,"sep",9,"oct",10,"nov",11,"dec",12,"no month") -> 2 | C857: =LEFT('All Transactions'!$E857,3) -> Feb | D857: =RIGHT(E857,4) -> 2026 | E857: Feb 24, 2026 | F857: 12:08 pm | G857: CREDIT | H857: 1 | I857: Cashback from PhonePe Gift Card | J857: T2602241208084032157414 | L857: Credited to | M857: =TEXT(A857,"dddd") -> Tuesday | N857: =DATE(Table4[[#This Row],[year]],Table4[[#This Row],[month2]],Table4[[#This Row],[day]]) -> 46077
A858: =MID(E858,5,2) -> 24 | B858: =_xlfn.SWITCH(Table4[[#This Row],[month]],"jan",1,"feb",2,"mar",3,"apr",4,"may",5,"jun",6,"jul",7,"aug",8,"sep",9,"oct",10,"nov",11,"dec",12,"no month") -> 2 | C858: =LEFT('All Transactions'!$E858,3) -> Feb | D858: =RIGHT(E858,4) -> 2026 | E858: Feb 24, 2026 | F858: 12:07 pm | G858: CREDIT | H858: 2.5 | I858: Cashback from PhonePe Gift Card | J858: T2602241207533286139354 | L858: Credited to | M858: =TEXT(A858,"dddd") -> Tuesday | N858: =DATE(Table4[[#This Row],[year]],Table4[[#This Row],[month2]],Table4[[#This Row],[day]]) -> 46077
A859: =MID(E859,5,2) -> 24 | B859: =_xlfn.SWITCH(Table4[[#This Row],[month]],"jan",1,"feb",2,"mar",3,"apr",4,"may",5,"jun",6,"jul",7,"aug",8,"sep",9,"oct",10,"nov",11,"dec",12,"no month") -> 2 | C859: =LEFT('All Transactions'!$E859,3) -> Feb | D859: =RIGHT(E859,4) -> 2026 | E859: Feb 24, 2026 | F859: 12:07 pm | G859: CREDIT | H859: 1 | I859: Cashback from PhonePe Gift Card | J859: T2602241207459160484970 | L859: Credited to | M859: =TEXT(A859,"dddd") -> Tuesday | N859: =DATE(Table4[[#This Row],[year]],Table4[[#This Row],[month2]],Table4[[#This Row],[day]]) -> 46077
A860: =MID(E860,5,2) -> 24 | B860: =_xlfn.SWITCH(Table4[[#This Row],[month]],"jan",1,"feb",2,"mar",3,"apr",4,"may",5,"jun",6,"jul",7,"aug",8,"sep",9,"oct",10,"nov",11,"dec",12,"no month") -> 2 | C860: =LEFT('All Transactions'!$E860,3) -> Feb | D860: =RIGHT(E860,4) -> 2026 | E860: Feb 24, 2026 | F860: 11:45 am | G860: DEBIT | H860: 40 | I860: Paid to GOVINDAARAPU RAJU | J860: T2602241145268772709714 | K860: 839253122102 | L860: Paid by XXXXXXXX1137 | M860: =TEXT(A860,"dddd") -> Tuesday | N860: =DATE(Table4[[#This Row],[year]],Table4[[#This Row],[month2]],Table4[[#This Row],[day]]) -> 46077
A861: =MID(E861,5,2) -> 24 | B861: =_xlfn.SWITCH(Table4[[#This Row],[month]],"jan",1,"feb",2,"mar",3,"apr",4,"may",5,"jun",6,"jul",7,"aug",8,"sep",9,"oct",10,"nov",11,"dec",12,"no month") -> 2 | C861: =LEFT('All Transactions'!$E861,3) -> Feb | D861: =RIGHT(E861,4) -> 2026 | E861: Feb 24, 2026 | F861: 12:01 am | G861: DEBIT | H861: 20 | I861: Paid to LAIBAS CAFE | J861: T2602240001009736939055 | K861: 188577753829 | L861: Paid by XXXXXXXX1137 | M861: =TEXT(A861,"dddd") -> Tuesday | N861: =DATE(Table4[[#This Row],[year]],Table4[[#This Row],[month2]],Table4[[#This Row],[day]]) -> 46077
A862: =MID(E862,5,2) -> 23 | B862: =_xlfn.SWITCH(Table4[[#This Row],[month]],"jan",1,"feb",2,"mar",3,"apr",4,"may",5,"jun",6,"jul",7,"aug",8,"sep",9,"oct",10,"nov",11,"dec",12,"no month") -> 2 | C862: =LEFT('All Transactions'!$E862,3) -> Feb | D862: =RIGHT(E862,4) -> 2026 | E862: Feb 23, 2026 | F862: 11:29 pm | G862: DEBIT | H862: 102.44 | I862: Paid to ZOMATO LIMITED | J862: T2602232329469327009466 | K862: 326608300898 | L862: Paid by XXXXXXXX1137 | M862: =TEXT(A862,"dddd") -> Monday | N862: =DATE(Table4[[#This Row],[year]],Table4[[#This Row],[month2]],Table4[[#This Row],[day]]) -> 46076
A863: =MID(E863,5,2) -> 23 | B863: =_xlfn.SWITCH(Table4[[#This Row],[month]],"jan",1,"feb",2,"mar",3,"apr",4,"may",5,"jun",6,"jul",7,"aug",8,"sep",9,"oct",10,"nov",11,"dec",12,"no month") -> 2 | C863: =LEFT('All Transactions'!$E863,3) -> Feb | D863: =RIGHT(E863,4) -> 2026 | E863: Feb 23, 2026 | F863: 11:29 pm | G863: CREDIT | H863: 100 | I863: Received from Charan 💗 | J863: T2602232329299318865390 | K863: 240116073032 | L863: Credited to XXXXXXXX1137 | M863: =TEXT(A863,"dddd") -> Monday | N863: =DATE(Table4[[#This Row],[year]],Table4[[#This Row],[month2]],Table4[[#This Row],[day]]) -> 46076
A864: =MID(E864,5,2) -> 23 | B864: =_xlfn.SWITCH(Table4[[#This Row],[month]],"jan",1,"feb",2,"mar",3,"apr",4,"may",5,"jun",6,"jul",7,"aug",8,"sep",9,"oct",10,"nov",11,"dec",12,"no month") -> 2 | C864: =LEFT('All Transactions'!$E864,3) -> Feb | D864: =RIGHT(E864,4) -> 2026 | E864: Feb 23, 2026 | F864: 08:20 pm | G864: DEBIT | H864: 470 | I864: Paid to KULDEEP CHHETRI | J864: T2602232020408236557082 | K864: 788944154797 | L864: Paid by XXXXXXXX1137 | M864: =TEXT(A864,"dddd") -> Monday | N864: =DATE(Table4[[#This Row],[year]],Table4[[#This Row],[month2]],Table4[[#This Row],[day]]) -> 46076
A865: =MID(E865,5,2) -> 23 | B865: =_xlfn.SWITCH(Table4[[#This Row],[month]],"jan",1,"feb",2,"mar",3,"apr",4,"may",5,"jun",6,"jul",7,"aug",8,"sep",9,"oct",10,"nov",11,"dec",12,"no month") -> 2 | C865: =LEFT('All Transactions'!$E865,3) -> Feb | D865: =RIGHT(E865,4) -> 2026 | E865: Feb 23, 2026 | F865: 08:20 pm | G865: CREDIT | H865: 200 | I865: Received from Charan 💗 | J865: T2602232020262586057040 | K865: 772024139307 | L865: Credited to XXXXXXXX1137 | M865: =TEXT(A865,"dddd") -> Monday | N865: =DATE(Table4[[#This Row],[year]],Table4[[#This Row],[month2]],Table4[[#This Row],[day]]) -> 46076
A866: =MID(E866,5,2) -> 23 | B866: =_xlfn.SWITCH(Table4[[#This Row],[month]],"jan",1,"feb",2,"mar",3,"apr",4,"may",5,"jun",6,"jul",7,"aug",8,"sep",9,"oct",10,"nov",11,"dec",12,"no month") -> 2 | C866: =LEFT('All Transactions'!$E866,3) -> Feb | D866: =RIGHT(E866,4) -> 2026 | E866: Feb 23, 2026 | F866: 08:17 pm | G866: CREDIT | H866: 200 | I866: Received from Manikanta | J866: T2602232017391167746726 | K866: 899351920465 | L866: Credited to XXXXXXXX1137 | M866: =TEXT(A866,"dddd") -> Monday | N866: =DATE(Table4[[#This Row],[year]],Table4[[#This Row],[month2]],Table4[[#This Row],[day]]) -> 46076
A867: =MID(E867,5,2) -> 23 | B867: =_xlfn.SWITCH(Table4[[#This Row],[month]],"jan",1,"feb",2,"mar",3,"apr",4,"may",5,"jun",6,"jul",7,"aug",8,"sep",9,"oct",10,"nov",11,"dec",12,"no month") -> 2 | C867: =LEFT('All Transactions'!$E867,3) -> Feb | D867: =RIGHT(E867,4) -> 2026 | E867: Feb 23, 2026 | F867: 07:29 pm | G867: DEBIT | H867: 120 | I867: Paid to Charan 💗 | J867: T2602231929382187452670 | K867: 981023739573 | L867: Paid by XXXXXXXX1137 | M867: =TEXT(A867,"dddd") -> Monday | N867: =DATE(Table4[[#This Row],[year]],Table4[[#This Row],[month2]],Table4[[#This Row],[day]]) -> 46076
A868: =MID(E868,5,2) -> 23 | B868: =_xlfn.SWITCH(Table4[[#This Row],[month]],"jan",1,"feb",2,"mar",3,"apr",4,"may",5,"jun",6,"jul",7,"aug",8,"sep",9,"oct",10,"nov",11,"dec",12,"no month") -> 2 | C868: =LEFT('All Transactions'!$E868,3) -> Feb | D868: =RIGHT(E868,4) -> 2026 | E868: Feb 23, 2026 | F868: 11:49 am | G868: DEBIT | H868: 20 | I868: Paid to SAI YOGESHWARA KIRANAM AND GENERAL STORE Gift Card | J868: T2602231149357725168833 | L868: Paid by | M868: =TEXT(A868,"dddd") -> Monday | N868: =DATE(Table4[[#This Row],[year]],Table4[[#This Row],[month2]],Table4[[#This Row],[day]]) -> 46076
A869: =MID(E869,5,2) -> 23 | B869: =_xlfn.SWITCH(Table4[[#This Row],[month]],"jan",1,"feb",2,"mar",3,"apr",4,"may",5,"jun",6,"jul",7,"aug",8,"sep",9,"oct",10,"nov",11,"dec",12,"no month") -> 2 | C869: =LEFT('All Transactions'!$E869,3) -> Feb | D869: =RIGHT(E869,4) -> 2026 | E869: Feb 23, 2026 | F869: 02:34 am | G869: CREDIT | H869: 4 | I869: Cashback from PhonePe Gift Card | J869: T2602230234153307094677 | L869: Credited to | M869: =TEXT(A869,"dddd") -> Monday | N869: =DATE(Table4[[#This Row],[year]],Table4[[#This Row],[month2]],Table4[[#This Row],[day]]) -> 46076
A870: =MID(E870,5,2) -> 23 | B870: =_xlfn.SWITCH(Table4[[#This Row],[month]],"jan",1,"feb",2,"mar",3,"apr",4,"may",5,"jun",6,"jul",7,"aug",8,"sep",9,"oct",10,"nov",11,"dec",12,"no month") -> 2 | C870: =LEFT('All Transactions'!$E870,3) -> Feb | D870: =RIGHT(E870,4) -> 2026 | E870: Feb 23, 2026 | F870: 02:30 am | G870: DEBIT | H870: 124.18 | I870: Paid to ZOMATO | J870: T2602230230239042553136 | K870: 133540710772 | L870: Paid by XXXXXXXX1137 | M870: =TEXT(A870,"dddd") -> Monday | N870: =DATE(Table4[[#This Row],[year]],Table4[[#This Row],[month2]],Table4[[#This Row],[day]]) -> 46076
A871: =MID(E871,5,2) -> 23 | B871: =_xlfn.SWITCH(Table4[[#This Row],[month]],"jan",1,"feb",2,"mar",3,"apr",4,"may",5,"jun",6,"jul",7,"aug",8,"sep",9,"oct",10,"nov",11,"dec",12,"no month") -> 2 | C871: =LEFT('All Transactions'!$E871,3) -> Feb | D871: =RIGHT(E871,4) -> 2026 | E871: Feb 23, 2026 | F871: 02:10 am | G871: CREDIT | H871: 1.5 | I871: Cashback from PhonePe Gift Card | J871: T2602230210374879286566 | L871: Credited to | M871: =TEXT(A871,"dddd") -> Monday | N871: =DATE(Table4[[#This Row],[year]],Table4[[#This Row],[month2]],Table4[[#This Row],[day]]) -> 46076
A872: =MID(E872,5,2) -> 23 | B872: =_xlfn.SWITCH(Table4[[#This Row],[month]],"jan",1,"feb",2,"mar",3,"apr",4,"may",5,"jun",6,"jul",7,"aug",8,"sep",9,"oct",10,"nov",11,"dec",12,"no month") -> 2 | C872: =LEFT('All Transactions'!$E872,3) -> Feb | D872: =RIGHT(E872,4) -> 2026 | E872: Feb 23, 2026 | F872: 01:53 am | G872: DEBIT | H872: 134 | I872: Paid to SHAIK YOUSUF | J872: T2602230153045912015641 | K872: 474049257385 | L872: Paid by XXXXXXXX1137 | M872: =TEXT(A872,"dddd") -> Monday | N872: =DATE(Table4[[#This Row],[year]],Table4[[#This Row],[month2]],Table4[[#This Row],[day]]) -> 46076
A873: =MID(E873,5,2) -> 23 | B873: =_xlfn.SWITCH(Table4[[#This Row],[month]],"jan",1,"feb",2,"mar",3,"apr",4,"may",5,"jun",6,"jul",7,"aug",8,"sep",9,"oct",10,"nov",11,"dec",12,"no month") -> 2 | C873: =LEFT('All Transactions'!$E873,3) -> Feb | D873: =RIGHT(E873,4) -> 2026 | E873: Feb 23, 2026 | F873: 01:31 am | G873: CREDIT | H873: 134 | I873: Received from BINGI VENKAT SAI | J873: T2602230131283793117402 | K873: 119024734012 | L873: Credited to XXXXXXXX1137 | M873: =TEXT(A873,"dddd") -> Monday | N873: =DATE(Table4[[#This Row],[year]],Table4[[#This Row],[month2]],Table4[[#This Row],[day]]) -> 46076
A874: =MID(E874,5,2) -> 23 | B874: =_xlfn.SWITCH(Table4[[#This Row],[month]],"jan",1,"feb",2,"mar",3,"apr",4,"may",5,"jun",6,"jul",7,"aug",8,"sep",9,"oct",10,"nov",11,"dec",12,"no month") -> 2 | C874: =LEFT('All Transactions'!$E874,3) -> Feb | D874: =RIGHT(E874,4) -> 2026 | E874: Feb 23, 2026 | F874: 12:53 am | G874: DEBIT | H874: 60 | I874: Paid to LAIBAS CAFE | J874: T2602230053502561644206 | K874: 234536505106 | L874: Paid by XXXXXXXX1137 | M874: =TEXT(A874,"dddd") -> Monday | N874: =DATE(Table4[[#This Row],[year]],Table4[[#This Row],[month2]],Table4[[#This Row],[day]]) -> 46076
A875: =MID(E875,5,2) -> 22 | B875: =_xlfn.SWITCH(Table4[[#This Row],[month]],"jan",1,"feb",2,"mar",3,"apr",4,"may",5,"jun",6,"jul",7,"aug",8,"sep",9,"oct",10,"nov",11,"dec",12,"no month") -> 2 | C875: =LEFT('All Transactions'!$E875,3) -> Feb | D875: =RIGHT(E875,4) -> 2026 | E875: Feb 22, 2026 | F875: 09:36 pm | G875: CREDIT | H875: 1.5 | I875: Cashback from PhonePe Gift Card | J875: T2602222136196321484171 | L875: Credited to | M875: =TEXT(A875,"dddd") -> Sunday | N875: =DATE(Table4[[#This Row],[year]],Table4[[#This Row],[month2]],Table4[[#This Row],[day]]) -> 46075
A876: =MID(E876,5,2) -> 22 | B876: =_xlfn.SWITCH(Table4[[#This Row],[month]],"jan",1,"feb",2,"mar",3,"apr",4,"may",5,"jun",6,"jul",7,"aug",8,"sep",9,"oct",10,"nov",11,"dec",12,"no month") -> 2 | C876: =LEFT('All Transactions'!$E876,3) -> Feb | D876: =RIGHT(E876,4) -> 2026 | E876: Feb 22, 2026 | F876: 09:36 pm | G876: DEBIT | H876: 24 | I876: Paid to Asian Tea Gift Card | J876: T2602222136038989145476 | L876: Paid by | M876: =TEXT(A876,"dddd") -> Sunday | N876: =DATE(Table4[[#This Row],[year]],Table4[[#This Row],[month2]],Table4[[#This Row],[day]]) -> 46075
A877: =MID(E877,5,2) -> 22 | B877: =_xlfn.SWITCH(Table4[[#This Row],[month]],"jan",1,"feb",2,"mar",3,"apr",4,"may",5,"jun",6,"jul",7,"aug",8,"sep",9,"oct",10,"nov",11,"dec",12,"no month") -> 2 | C877: =LEFT('All Transactions'!$E877,3) -> Feb | D877: =RIGHT(E877,4) -> 2026 | E877: Feb 22, 2026 | F877: 07:51 pm | G877: DEBIT | H877: 30 | I877: Paid to JAGDAMBA MITHAI BHANDAR | J877: T2602221951207970278059 | K877: 092536714577 | L877: Paid by XXXXXXXX1137 | M877: =TEXT(A877,"dddd") -> Sunday | N877: =DATE(Table4[[#This Row],[year]],Table4[[#This Row],[month2]],Table4[[#This Row],[day]]) -> 46075
A878: =MID(E878,5,2) -> 22 | B878: =_xlfn.SWITCH(Table4[[#This Row],[month]],"jan",1,"feb",2,"mar",3,"apr",4,"may",5,"jun",6,"jul",7,"aug",8,"sep",9,"oct",10,"nov",11,"dec",12,"no month") -> 2 | C878: =LEFT('All Transactions'!$E878,3) -> Feb | D878: =RIGHT(E878,4) -> 2026 | E878: Feb 22, 2026 | F878: 06:46 pm | G878: CREDIT | H878: 1.5 | I878: Cashback from PhonePe Gift Card | J878: T2602221846212631451141 | L878: Credited to | M878: =TEXT(A878,"dddd") -> Sunday | N878: =DATE(Table4[[#This Row],[year]],Table4[[#This Row],[month2]],Table4[[#This Row],[day]]) -> 46075
A879: =MID(E879,5,2) -> 22 | B879: =_xlfn.SWITCH(Table4[[#This Row],[month]],"jan",1,"feb",2,"mar",3,"apr",4,"may",5,"jun",6,"jul",7,"aug",8,"sep",9,"oct",10,"nov",11,"dec",12,"no month") -> 2 | C879: =LEFT('All Transactions'!$E879,3) -> Feb | D879: =RIGHT(E879,4) -> 2026 | E879: Feb 22, 2026 | F879: 06:46 pm | G879: CREDIT | H879: 1 | I879: Cashback from PhonePe Gift Card | J879: T2602221846080305260048 | L879: Credited to | M879: =TEXT(A879,"dddd") -> Sunday | N879: =DATE(Table4[[#This Row],[year]],Table4[[#This Row],[month2]],Table4[[#This Row],[day]]) -> 46075
A880: =MID(E880,5,2) -> 22 | B880: =_xlfn.SWITCH(Table4[[#This Row],[month]],"jan",1,"feb",2,"mar",3,"apr",4,"may",5,"jun",6,"jul",7,"aug",8,"sep",9,"oct",10,"nov",11,"dec",12,"no month") -> 2 | C880: =LEFT('All Transactions'!$E880,3) -> Feb | D880: =RIGHT(E880,4) -> 2026 | E880: Feb 22, 2026 | F880: 06:45 pm | G880: CREDIT | H880: 2 | I880: Cashback from PhonePe Gift Card | J880: T2602221845588005854318 | L880: Credited to | M880: =TEXT(A880,"dddd") -> Sunday | N880: =DATE(Table4[[#This Row],[year]],Table4[[#This Row],[month2]],Table4[[#This Row],[day]]) -> 46075
A881: =MID(E881,5,2) -> 22 | B881: =_xlfn.SWITCH(Table4[[#This Row],[month]],"jan",1,"feb",2,"mar",3,"apr",4,"may",5,"jun",6,"jul",7,"aug",8,"sep",9,"oct",10,"nov",11,"dec",12,"no month") -> 2 | C881: =LEFT('All Transactions'!$E881,3) -> Feb | D881: =RIGHT(E881,4) -> 2026 | E881: Feb 22, 2026 | F881: 06:45 pm | G881: CREDIT | H881: 1 | I881: Cashback from PhonePe Gift Card | J881: T2602221845503934540699 | L881: Credited to | M881: =TEXT(A881,"dddd") -> Sunday | N881: =DATE(Table4[[#This Row],[year]],Table4[[#This Row],[month2]],Table4[[#This Row],[day]]) -> 46075
A882: =MID(E882,5,2) -> 22 | B882: =_xlfn.SWITCH(Table4[[#This Row],[month]],"jan",1,"feb",2,"mar",3,"apr",4,"may",5,"jun",6,"jul",7,"aug",8,"sep",9,"oct",10,"nov",11,"dec",12,"no month") -> 2 | C882: =LEFT('All Transactions'!$E882,3) -> Feb | D882: =RIGHT(E882,4) -> 2026 | E882: Feb 22, 2026 | F882: 06:45 pm | G882: CREDIT | H882: 1.5 | I882: Cashback from PhonePe Gift Card | J882: T2602221845423977027319 | L882: Credited to | M882: =TEXT(A882,"dddd") -> Sunday | N882: =DATE(Table4[[#This Row],[year]],Table4[[#This Row],[month2]],Table4[[#This Row],[day]]) -> 46075
A883: =MID(E883,5,2) -> 22 | B883: =_xlfn.SWITCH(Table4[[#This Row],[month]],"jan",1,"feb",2,"mar",3,"apr",4,"may",5,"jun",6,"jul",7,"aug",8,"sep",9,"oct",10,"nov",11,"dec",12,"no month") -> 2 | C883: =LEFT('All Transactions'!$E883,3) -> Feb | D883: =RIGHT(E883,4) -> 2026 | E883: Feb 22, 2026 | F883: 06:45 pm | G883: CREDIT | H883: 1.5 | I883: Cashback from PhonePe Gift Card | J883: T2602221845397632729223 | L883: Credited to | M883: =TEXT(A883,"dddd") -> Sunday | N883: =DATE(Table4[[#This Row],[year]],Table4[[#This Row],[month2]],Table4[[#This Row],[day]]) -> 46075
A884: =MID(E884,5,2) -> 22 | B884: =_xlfn.SWITCH(Table4[[#This Row],[month]],"jan",1,"feb",2,"mar",3,"apr",4,"may",5,"jun",6,"jul",7,"aug",8,"sep",9,"oct",10,"nov",11,"dec",12,"no month") -> 2 | C884: =LEFT('All Transactions'!$E884,3) -> Feb | D884: =RIGHT(E884,4) -> 2026 | E884: Feb 22, 2026 | F884: 06:45 pm | G884: CREDIT | H884: 3 | I884: Cashback from PhonePe Gift Card | J884: T2602221845364062729161 | L884: Credited to | M884: =TEXT(A884,"dddd") -> Sunday | N884: =DATE(Table4[[#This Row],[year]],Table4[[#This Row],[month2]],Table4[[#This Row],[day]]) -> 46075
A885: =MID(E885,5,2) -> 22 | B885: =_xlfn.SWITCH(Table4[[#This Row],[month]],"jan",1,"feb",2,"mar",3,"apr",4,"may",5,"jun",6,"jul",7,"aug",8,"sep",9,"oct",10,"nov",11,"dec",12,"no month") -> 2 | C885: =LEFT('All Transactions'!$E885,3) -> Feb | D885: =RIGHT(E885,4) -> 2026 | E885: Feb 22, 2026 | F885: 06:45 pm | G885: CREDIT | H885: 1.5 | I885: Cashback from PhonePe Gift Card | J885: T2602221845334351834098 | L885: Credited to | M885: =TEXT(A885,"dddd") -> Sunday | N885: =DATE(Table4[[#This Row],[year]],Table4[[#This Row],[month2]],Table4[[#This Row],[day]]) -> 46075
A886: =MID(E886,5,2) -> 22 | B886: =_xlfn.SWITCH(Table4[[#This Row],[month]],"jan",1,"feb",2,"mar",3,"apr",4,"may",5,"jun",6,"jul",7,"aug",8,"sep",9,"oct",10,"nov",11,"dec",12,"no month") -> 2 | C886: =LEFT('All Transactions'!$E886,3) -> Feb | D886: =RIGHT(E886,4) -> 2026 | E886: Feb 22, 2026 | F886: 06:45 pm | G886: CREDIT | H886: 4 | I886: Cashback from PhonePe Gift Card | J886: T2602221845302370256502 | L886: Credited to | M886: =TEXT(A886,"dddd") -> Sunday | N886: =DATE(Table4[[#This Row],[year]],Table4[[#This Row],[month2]],Table4[[#This Row],[day]]) -> 46075
A887: =MID(E887,5,2) -> 22 | B887: =_xlfn.SWITCH(Table4[[#This Row],[month]],"jan",1,"feb",2,"mar",3,"apr",4,"may",5,"jun",6,"jul",7,"aug",8,"sep",9,"oct",10,"nov",11,"dec",12,"no month") -> 2 | C887: =LEFT('All Transactions'!$E887,3) -> Feb | D887: =RIGHT(E887,4) -> 2026 | E887: Feb 22, 2026 | F887: 06:45 pm | G887: CREDIT | H887: 4 | I887: Cashback from PhonePe Gift Card | J887: T2602221845270010378632 | L887: Credited to | M887: =TEXT(A887,"dddd") -> Sunday | N887: =DATE(Table4[[#This Row],[year]],Table4[[#This Row],[month2]],Table4[[#This Row],[day]]) -> 46075
A888: =MID(E888,5,2) -> 22 | B888: =_xlfn.SWITCH(Table4[[#This Row],[month]],"jan",1,"feb",2,"mar",3,"apr",4,"may",5,"jun",6,"jul",7,"aug",8,"sep",9,"oct",10,"nov",11,"dec",12,"no month") -> 2 | C888: =LEFT('All Transactions'!$E888,3) -> Feb | D888: =RIGHT(E888,4) -> 2026 | E888: Feb 22, 2026 | F888: 06:45 pm | G888: CREDIT | H888: 4 | I888: Cashback from PhonePe Gift Card | J888: T2602221845234763697774 | L888: Credited to | M888: =TEXT(A888,"dddd") -> Sunday | N888: =DATE(Table4[[#This Row],[year]],Table4[[#This Row],[month2]],Table4[[#This Row],[day]]) -> 46075
A889: =MID(E889,5,2) -> 22 | B889: =_xlfn.SWITCH(Table4[[#This Row],[month]],"jan",1,"feb",2,"mar",3,"apr",4,"may",5,"jun",6,"jul",7,"aug",8,"sep",9,"oct",10,"nov",11,"dec",12,"no month") -> 2 | C889: =LEFT('All Transactions'!$E889,3) -> Feb | D889: =RIGHT(E889,4) -> 2026 | E889: Feb 22, 2026 | F889: 06:45 pm | G889: CREDIT | H889: 2.5 | I889: Cashback from PhonePe Gift Card | J889: T2602221845199725921804 | L889: Credited to | M889: =TEXT(A889,"dddd") -> Sunday | N889: =DATE(Table4[[#This Row],[year]],Table4[[#This Row],[month2]],Table4[[#This Row],[day]]) -> 46075
... A896: =MID(E896,5,2) -> 22 | B896: =_xlfn.SWITCH(Table4[[#This Row],[month]],"jan",1,"feb",2,"mar",3,"apr",4,"may",5,"jun",6,"jul",7,"aug",8,"sep",9,"oct",10,"nov",11,"dec",12,"no month") -> 2 | C896: =LEFT('All Transactions'!$E896,3) -> Feb | D896: =RIGHT(E896,4) -> 2026 | E896: Feb 22, 2026 | F896: 06:44 pm | G896: CREDIT | H896: 2 | I896: Cashback from PhonePe Gift Card | J896: T2602221844515557043239 | L896: Credited to | M896: =TEXT(A896,"dddd") -> Sunday | N896: =DATE(Table4[[#This Row],[year]],Table4[[#This Row],[month2]],Table4[[#This Row],[day]]) -> 46075
A897: =MID(E897,5,2) -> 22 | B897: =_xlfn.SWITCH(Table4[[#This Row],[month]],"jan",1,"feb",2,"mar",3,"apr",4,"may",5,"jun",6,"jul",7,"aug",8,"sep",9,"oct",10,"nov",11,"dec",12,"no month") -> 2 | C897: =LEFT('All Transactions'!$E897,3) -> Feb | D897: =RIGHT(E897,4) -> 2026 | E897: Feb 22, 2026 | F897: 06:43 pm | G897: DEBIT | H897: 200 | I897: Paid to Manikanta | J897: T2602221843135985699161 | K897: 853343126888 | L897: Paid by XXXXXXXX1137 | M897: =TEXT(A897,"dddd") -> Sunday | N897: =DATE(Table4[[#This Row],[year]],Table4[[#This Row],[month2]],Table4[[#This Row],[day]]) -> 46075
A898: =MID(E898,5,2) -> 22 | B898: =_xlfn.SWITCH(Table4[[#This Row],[month]],"jan",1,"feb",2,"mar",3,"apr",4,"may",5,"jun",6,"jul",7,"aug",8,"sep",9,"oct",10,"nov",11,"dec",12,"no month") -> 2 | C898: =LEFT('All Transactions'!$E898,3) -> Feb | D898: =RIGHT(E898,4) -> 2026 | E898: Feb 22, 2026 | F898: 06:41 pm | G898: CREDIT | H898: 1000 | I898: Received from Daddy | J898: T2602221841184869145174 | K898: 764563591268 | L898: Credited to XXXXXXXX1137 | M898: =TEXT(A898,"dddd") -> Sunday | N898: =DATE(Table4[[#This Row],[year]],Table4[[#This Row],[month2]],Table4[[#This Row],[day]]) -> 46075
A899: =MID(E899,5,2) -> 22 | B899: =_xlfn.SWITCH(Table4[[#This Row],[month]],"jan",1,"feb",2,"mar",3,"apr",4,"may",5,"jun",6,"jul",7,"aug",8,"sep",9,"oct",10,"nov",11,"dec",12,"no month") -> 2 | C899: =LEFT('All Transactions'!$E899,3) -> Feb | D899: =RIGHT(E899,4) -> 2026 | E899: Feb 22, 2026 | F899: 02:25 pm | G899: CREDIT | H899: 200 | I899: Received from BINGI VENKAT SAI | J899: T2602221425238801266894 | K899: 119000058299 | L899: Credited to XXXXXXXX1137 | M899: =TEXT(A899,"dddd") -> Sunday | N899: =DATE(Table4[[#This Row],[year]],Table4[[#This Row],[month2]],Table4[[#This Row],[day]]) -> 46075
A900: =MID(E900,5,2) -> 22 | B900: =_xlfn.SWITCH(Table4[[#This Row],[month]],"jan",1,"feb",2,"mar",3,"apr",4,"may",5,"jun",6,"jul",7,"aug",8,"sep",9,"oct",10,"nov",11,"dec",12,"no month") -> 2 | C900: =LEFT('All Transactions'!$E900,3) -> Feb | D900: =RIGHT(E900,4) -> 2026 | E900: Feb 22, 2026 | F900: 02:10 pm | G900: DEBIT | H900: 80 | I900: Paid to GOVINDAARAPU RAJU | J900: T2602221410143808963831 | K900: 908290981479 | L900: Paid by XXXXXXXX1137 | M900: =TEXT(A900,"dddd") -> Sunday | N900: =DATE(Table4[[#This Row],[year]],Table4[[#This Row],[month2]],Table4[[#This Row],[day]]) -> 46075
A901: =MID(E901,5,2) -> 22 | B901: =_xlfn.SWITCH(Table4[[#This Row],[month]],"jan",1,"feb",2,"mar",3,"apr",4,"may",5,"jun",6,"jul",7,"aug",8,"sep",9,"oct",10,"nov",11,"dec",12,"no month") -> 2 | C901: =LEFT('All Transactions'!$E901,3) -> Feb | D901: =RIGHT(E901,4) -> 2026 | E901: Feb 22, 2026 | F901: 02:09 pm | G901: CREDIT | H901: 40 | I901: Received from Ashwik Reddy | J901: T2602221409480553256943 | K901: 629917450886 | L901: Credited to XXXXXXXX1137 | M901: =TEXT(A901,"dddd") -> Sunday | N901: =DATE(Table4[[#This Row],[year]],Table4[[#This Row],[month2]],Table4[[#This Row],[day]]) -> 46075
A902: =MID(E902,5,2) -> 22 | B902: =_xlfn.SWITCH(Table4[[#This Row],[month]],"jan",1,"feb",2,"mar",3,"apr",4,"may",5,"jun",6,"jul",7,"aug",8,"sep",9,"oct",10,"nov",11,"dec",12,"no month") -> 2 | C902: =LEFT('All Transactions'!$E902,3) -> Feb | D902: =RIGHT(E902,4) -> 2026 | E902: Feb 22, 2026 | F902: 02:04 pm | G902: CREDIT | H902: 40 | I902: Received from Ashwik Reddy | J902: T2602221404279172128661 | K902: 623350704063 | L902: Credited to XXXXXXXX1137 | M902: =TEXT(A902,"dddd") -> Sunday | N902: =DATE(Table4[[#This Row],[year]],Table4[[#This Row],[month2]],Table4[[#This Row],[day]]) -> 46075
A903: =MID(E903,5,2) -> 21 | B903: =_xlfn.SWITCH(Table4[[#This Row],[month]],"jan",1,"feb",2,"mar",3,"apr",4,"may",5,"jun",6,"jul",7,"aug",8,"sep",9,"oct",10,"nov",11,"dec",12,"no month") -> 2 | C903: =LEFT('All Transactions'!$E903,3) -> Feb | D903: =RIGHT(E903,4) -> 2026 | E903: Feb 21, 2026 | F903: 09:37 pm | G903: DEBIT | H903: 153.2 | I903: Paid to ZOMATO LIMITED | J903: T2602212137333305462014 | K903: 751872838594 | L903: Paid by XXXXXXXX1137 | M903: =TEXT(A903,"dddd") -> Saturday | N903: =DATE(Table4[[#This Row],[year]],Table4[[#This Row],[month2]],Table4[[#This Row],[day]]) -> 46074
A904: =MID(E904,5,2) -> 21 | B904: =_xlfn.SWITCH(Table4[[#This Row],[month]],"jan",1,"feb",2,"mar",3,"apr",4,"may",5,"jun",6,"jul",7,"aug",8,"sep",9,"oct",10,"nov",11,"dec",12,"no month") -> 2 | C904: =LEFT('All Transactions'!$E904,3) -> Feb | D904: =RIGHT(E904,4) -> 2026 | E904: Feb 21, 2026 | F904: 09:37 pm | G904: CREDIT | H904: 5 | I904: Received from Manikanta | J904: T2602212137306442708662 | K904: 554136110448 | L904: Credited to XXXXXXXX1137 | M904: =TEXT(A904,"dddd") -> Saturday | N904: =DATE(Table4[[#This Row],[year]],Table4[[#This Row],[month2]],Table4[[#This Row],[day]]) -> 46074
A905: =MID(E905,5,2) -> 21 | B905: =_xlfn.SWITCH(Table4[[#This Row],[month]],"jan",1,"feb",2,"mar",3,"apr",4,"may",5,"jun",6,"jul",7,"aug",8,"sep",9,"oct",10,"nov",11,"dec",12,"no month") -> 2 | C905: =LEFT('All Transactions'!$E905,3) -> Feb | D905: =RIGHT(E905,4) -> 2026 | E905: Feb 21, 2026 | F905: 09:27 pm | G905: CREDIT | H905: 150 | I905: Received from Abhi 💗 | J905: T2602212127147033033077 | K905: 757419656026 | L905: Credited to XXXXXXXX1137 | M905: =TEXT(A905,"dddd") -> Saturday | N905: =DATE(Table4[[#This Row],[year]],Table4[[#This Row],[month2]],Table4[[#This Row],[day]]) -> 46074
A906: =MID(E906,5,2) -> 21 | B906: =_xlfn.SWITCH(Table4[[#This Row],[month]],"jan",1,"feb",2,"mar",3,"apr",4,"may",5,"jun",6,"jul",7,"aug",8,"sep",9,"oct",10,"nov",11,"dec",12,"no month") -> 2 | C906: =LEFT('All Transactions'!$E906,3) -> Feb | D906: =RIGHT(E906,4) -> 2026 | E906: Feb 21, 2026 | F906: 02:18 pm | G906: DEBIT | H906: 30 | I906: Paid to GOVINDAARAPU RAJU | J906: T2602211418291400163373 | K906: 575475710417 | L906: Paid by XXXXXXXX1137 | M906: =TEXT(A906,"dddd") -> Saturday | N906: =DATE(Table4[[#This Row],[year]],Table4[[#This Row],[month2]],Table4[[#This Row],[day]]) -> 46074
A907: =MID(E907,5,2) -> 21 | B907: =_xlfn.SWITCH(Table4[[#This Row],[month]],"jan",1,"feb",2,"mar",3,"apr",4,"may",5,"jun",6,"jul",7,"aug",8,"sep",9,"oct",10,"nov",11,"dec",12,"no month") -> 2 | C907: =LEFT('All Transactions'!$E907,3) -> Feb | D907: =RIGHT(E907,4) -> 2026 | E907: Feb 21, 2026 | F907: 02:18 pm | G907: CREDIT | H907: 30 | I907: Received from Abhi 💗 | J907: T2602211418228516419584 | K907: 991008137863 | L907: Credited to XXXXXXXX1137 | M907: =TEXT(A907,"dddd") -> Saturday | N907: =DATE(Table4[[#This Row],[year]],Table4[[#This Row],[month2]],Table4[[#This Row],[day]]) -> 46074
A908: =MID(E908,5,2) -> 21 | B908: =_xlfn.SWITCH(Table4[[#This Row],[month]],"jan",1,"feb",2,"mar",3,"apr",4,"may",5,"jun",6,"jul",7,"aug",8,"sep",9,"oct",10,"nov",11,"dec",12,"no month") -> 2 | C908: =LEFT('All Transactions'!$E908,3) -> Feb | D908: =RIGHT(E908,4) -> 2026 | E908: Feb 21, 2026 | F908: 12:51 pm | G908: DEBIT | H908: 30 | I908: Paid to SAI YOGESHWARA KIRANAM AND GENERAL STORE | J908: T2602211251103168618511 | K908: 341447524767 | L908: Paid by XXXXXXXX1137 | M908: =TEXT(A908,"dddd") -> Saturday | N908: =DATE(Table4[[#This Row],[year]],Table4[[#This Row],[month2]],Table4[[#This Row],[day]]) -> 46074
... A938: =MID(E938,5,2) -> 17 | B938: =_xlfn.SWITCH(Table4[[#This Row],[month]],"jan",1,"feb",2,"mar",3,"apr",4,"may",5,"jun",6,"jul",7,"aug",8,"sep",9,"oct",10,"nov",11,"dec",12,"no month") -> 2 | C938: =LEFT('All Transactions'!$E938,3) -> Feb | D938: =RIGHT(E938,4) -> 2026 | E938: Feb 17, 2026 | F938: 07:00 pm | G938: DEBIT | H938: 90 | I938: Paid to Sri Sai super cool drink 2 | J938: T2602171900165556046183 | K938: 494965278602 | L938: Paid by XXXXXXXX1137 | M938: =TEXT(A938,"dddd") -> Tuesday | N938: =DATE(Table4[[#This Row],[year]],Table4[[#This Row],[month2]],Table4[[#This Row],[day]]) -> 46070
A939: =MID(E939,5,2) -> 17 | B939: =_xlfn.SWITCH(Table4[[#This Row],[month]],"jan",1,"feb",2,"mar",3,"apr",4,"may",5,"jun",6,"jul",7,"aug",8,"sep",9,"oct",10,"nov",11,"dec",12,"no month") -> 2 | C939: =LEFT('All Transactions'!$E939,3) -> Feb | D939: =RIGHT(E939,4) -> 2026 | E939: Feb 17, 2026 | F939: 05:27 pm | G939: DEBIT | H939: 5000 | I939: Paid to NARSIMHA REDDY ENGINEERING COLLEGE TRAINING AND PLACEMENTS ICI48202605172702sGprdcVULQbTjPxg0c | K939: 109211984198 | L939: Paid by XXXXXXXX1137 | M939: =TEXT(A939,"dddd") -> Tuesday | N939: =DATE(Table4[[#This Row],[year]],Table4[[#This Row],[month2]],Table4[[#This Row],[day]]) -> 46070
A940: =MID(E940,5,2) -> 17 | B940: =_xlfn.SWITCH(Table4[[#This Row],[month]],"jan",1,"feb",2,"mar",3,"apr",4,"may",5,"jun",6,"jul",7,"aug",8,"sep",9,"oct",10,"nov",11,"dec",12,"no month") -> 2 | C940: =LEFT('All Transactions'!$E940,3) -> Feb | D940: =RIGHT(E940,4) -> 2026 | E940: Feb 17, 2026 | F940: 05:24 pm | G940: CREDIT | H940: 5000 | I940: Received from Manikanta | J940: T2602171724312572990078 | K940: 924802374420 | L940: Credited to XXXXXXXX1137 | M940: =TEXT(A940,"dddd") -> Tuesday | N940: =DATE(Table4[[#This Row],[year]],Table4[[#This Row],[month2]],Table4[[#This Row],[day]]) -> 46070
A941: =MID(E941,5,2) -> 17 | B941: =_xlfn.SWITCH(Table4[[#This Row],[month]],"jan",1,"feb",2,"mar",3,"apr",4,"may",5,"jun",6,"jul",7,"aug",8,"sep",9,"oct",10,"nov",11,"dec",12,"no month") -> 2 | C941: =LEFT('All Transactions'!$E941,3) -> Feb | D941: =RIGHT(E941,4) -> 2026 | E941: Feb 17, 2026 | F941: 04:27 pm | G941: DEBIT | H941: 5000 | I941: Paid to NARSIMHA REDDY ENGINEERING COLLEGE TRAINING AND PLACEMENTS ICI02202604172702RuJrP6NJMBVJciwqbk | K941: 109211617008 | L941: Paid by XXXXXXXX1137 | M941: =TEXT(A941,"dddd") -> Tuesday | N941: =DATE(Table4[[#This Row],[year]],Table4[[#This Row],[month2]],Table4[[#This Row],[day]]) -> 46070
A942: =MID(E942,5,2) -> 17 | B942: =_xlfn.SWITCH(Table4[[#This Row],[month]],"jan",1,"feb",2,"mar",3,"apr",4,"may",5,"jun",6,"jul",7,"aug",8,"sep",9,"oct",10,"nov",11,"dec",12,"no month") -> 2 | C942: =LEFT('All Transactions'!$E942,3) -> Feb | D942: =RIGHT(E942,4) -> 2026 | E942: Feb 17, 2026 | F942: 04:11 pm | G942: CREDIT | H942: 5000 | I942: Received from Babai | J942: T2602171611376794332055 | K942: 112916445424 | L942: Credited to XXXXXXXX1137 | M942: =TEXT(A942,"dddd") -> Tuesday | N942: =DATE(Table4[[#This Row],[year]],Table4[[#This Row],[month2]],Table4[[#This Row],[day]]) -> 46070
A943: =MID(E943,5,2) -> 17 | B943: =_xlfn.SWITCH(Table4[[#This Row],[month]],"jan",1,"feb",2,"mar",3,"apr",4,"may",5,"jun",6,"jul",7,"aug",8,"sep",9,"oct",10,"nov",11,"dec",12,"no month") -> 2 | C943: =LEFT('All Transactions'!$E943,3) -> Feb | D943: =RIGHT(E943,4) -> 2026 | E943: Feb 17, 2026 | F943: 07:03 am | G943: DEBIT | H943: 70 | I943: Paid to Sri Durga bhavani reddy tiffin centre | J943: T2602170703253438822828 | K943: 428896139677 | L943: Paid by XXXXXXXX1137 | M943: =TEXT(A943,"dddd") -> Tuesday | N943: =DATE(Table4[[#This Row],[year]],Table4[[#This Row],[month2]],Table4[[#This Row],[day]]) -> 46070
A944: =MID(E944,5,2) -> 16 | B944: =_xlfn.SWITCH(Table4[[#This Row],[month]],"jan",1,"feb",2,"mar",3,"apr",4,"may",5,"jun",6,"jul",7,"aug",8,"sep",9,"oct",10,"nov",11,"dec",12,"no month") -> 2 | C944: =LEFT('All Transactions'!$E944,3) -> Feb | D944: =RIGHT(E944,4) -> 2026 | E944: Feb 16, 2026 | F944: 09:54 pm | G944: DEBIT | H944: 50 | I944: Paid to sri krishna authana | J944: T2602162154170196129940 | K944: 313957042697 | L944: Paid by XXXXXXXX1137 | M944: =TEXT(A944,"dddd") -> Monday | N944: =DATE(Table4[[#This Row],[year]],Table4[[#This Row],[month2]],Table4[[#This Row],[day]]) -> 46069
A945: =MID(E945,5,2) -> 16 | B945: =_xlfn.SWITCH(Table4[[#This Row],[month]],"jan",1,"feb",2,"mar",3,"apr",4,"may",5,"jun",6,"jul",7,"aug",8,"sep",9,"oct",10,"nov",11,"dec",12,"no month") -> 2 | C945: =LEFT('All Transactions'!$E945,3) -> Feb | D945: =RIGHT(E945,4) -> 2026 | E945: Feb 16, 2026 | F945: 06:31 pm | G945: DEBIT | H945: 40 | I945: Paid to Kumar Fast Food | J945: T2602161831146949460089 | K945: 840559962425 | L945: Paid by XXXXXXXX1137 | M945: =TEXT(A945,"dddd") -> Monday | N945: =DATE(Table4[[#This Row],[year]],Table4[[#This Row],[month2]],Table4[[#This Row],[day]]) -> 46069
A946: =MID(E946,5,2) -> 16 | B946: =_xlfn.SWITCH(Table4[[#This Row],[month]],"jan",1,"feb",2,"mar",3,"apr",4,"may",5,"jun",6,"jul",7,"aug",8,"sep",9,"oct",10,"nov",11,"dec",12,"no month") -> 2 | C946: =LEFT('All Transactions'!$E946,3) -> Feb | D946: =RIGHT(E946,4) -> 2026 | E946: Feb 16, 2026 | F946: 06:02 pm | G946: DEBIT | H946: 12 | I946: Paid to BMTC BUS KA57F6005 | J946: T2602161802028573168236 | K946: 917677577953 | L946: Paid by XXXXXXXX1137 | M946: =TEXT(A946,"dddd") -> Monday | N946: =DATE(Table4[[#This Row],[year]],Table4[[#This Row],[month2]],Table4[[#This Row],[day]]) -> 46069
A947: =MID(E947,5,2) -> 16 | B947: =_xlfn.SWITCH(Table4[[#This Row],[month]],"jan",1,"feb",2,"mar",3,"apr",4,"may",5,"jun",6,"jul",7,"aug",8,"sep",9,"oct",10,"nov",11,"dec",12,"no month") -> 2 | C947: =LEFT('All Transactions'!$E947,3) -> Feb | D947: =RIGHT(E947,4) -> 2026 | E947: Feb 16, 2026 | F947: 02:05 pm | G947: DEBIT | H947: 161 | I947: Paid to ZOMATO | J947: T2602161405056046302461 | K947: 602368416752 | L947: Paid by XXXXXXXX1137 | M947: =TEXT(A947,"dddd") -> Monday | N947: =DATE(Table4[[#This Row],[year]],Table4[[#This Row],[month2]],Table4[[#This Row],[day]]) -> 46069
A948: =MID(E948,5,2) -> 16 | B948: =_xlfn.SWITCH(Table4[[#This Row],[month]],"jan",1,"feb",2,"mar",3,"apr",4,"may",5,"jun",6,"jul",7,"aug",8,"sep",9,"oct",10,"nov",11,"dec",12,"no month") -> 2 | C948: =LEFT('All Transactions'!$E948,3) -> Feb | D948: =RIGHT(E948,4) -> 2026 | E948: Feb 16, 2026 | F948: 01:24 pm | G948: CREDIT | H948: 200 | I948: Received from BINGI VENKAT SAI | J948: T2602161324155322495860 | K948: 118738283759 | L948: Credited to XXXXXXXX1137 | M948: =TEXT(A948,"dddd") -> Monday | N948: =DATE(Table4[[#This Row],[year]],Table4[[#This Row],[month2]],Table4[[#This Row],[day]]) -> 46069
A949: =MID(E949,5,2) -> 16 | B949: =_xlfn.SWITCH(Table4[[#This Row],[month]],"jan",1,"feb",2,"mar",3,"apr",4,"may",5,"jun",6,"jul",7,"aug",8,"sep",9,"oct",10,"nov",11,"dec",12,"no month") -> 2 | C949: =LEFT('All Transactions'!$E949,3) -> Feb | D949: =RIGHT(E949,4) -> 2026 | E949: Feb 16, 2026 | F949: 11:16 am | G949: DEBIT | H949: 60 | I949: Paid to RAM MEDICALS03 | J949: T2602161116162615945287 | K949: 415072721650 | L949: Paid by XXXXXXXX1137 | M949: =TEXT(A949,"dddd") -> Monday | N949: =DATE(Table4[[#This Row],[year]],Table4[[#This Row],[month2]],Table4[[#This Row],[day]]) -> 46069
A950: =MID(E950,5,2) -> 15 | B950: =_xlfn.SWITCH(Table4[[#This Row],[month]],"jan",1,"feb",2,"mar",3,"apr",4,"may",5,"jun",6,"jul",7,"aug",8,"sep",9,"oct",10,"nov",11,"dec",12,"no month") -> 2 | C950: =LEFT('All Transactions'!$E950,3) -> Feb | D950: =RIGHT(E950,4) -> 2026 | E950: Feb 15, 2026 | F950: 06:27 pm | G950: DEBIT | H950: 93 | I950: Paid to PRAVEEN KUMAR Y K | J950: T2602151827294427800784 | K950: 121410908181 | L950: Paid by XXXXXXXX1137 | M950: =TEXT(A950,"dddd") -> Sunday | N950: =DATE(Table4[[#This Row],[year]],Table4[[#This Row],[month2]],Table4[[#This Row],[day]]) -> 46068
A951: =MID(E951,5,2) -> 15 | B951: =_xlfn.SWITCH(Table4[[#This Row],[month]],"jan",1,"feb",2,"mar",3,"apr",4,"may",5,"jun",6,"jul",7,"aug",8,"sep",9,"oct",10,"nov",11,"dec",12,"no month") -> 2 | C951: =LEFT('All Transactions'!$E951,3) -> Feb | D951: =RIGHT(E951,4) -> 2026 | E951: Feb 15, 2026 | F951: 03:55 pm | G951: DEBIT | H951: 1600 | I951: Paid to ALLE MOHAN RAO | J951: T2602151555251325935322 | K951: 807622972860 | L951: Paid by XXXXXXXX1137 | M951: =TEXT(A951,"dddd") -> Sunday | N951: =DATE(Table4[[#This Row],[year]],Table4[[#This Row],[month2]],Table4[[#This Row],[day]]) -> 46068
A952: =MID(E952,5,2) -> 15 | B952: =_xlfn.SWITCH(Table4[[#This Row],[month]],"jan",1,"feb",2,"mar",3,"apr",4,"may",5,"jun",6,"jul",7,"aug",8,"sep",9,"oct",10,"nov",11,"dec",12,"no month") -> 2 | C952: =LEFT('All Transactions'!$E952,3) -> Feb | D952: =RIGHT(E952,4) -> 2026 | E952: Feb 15, 2026 | F952: 03:37 pm | G952: CREDIT | H952: 1000 | I952: Received from Bava 😘 | J952: T2602151537403889181922 | K952: 962758988553 | L952: Credited to XXXXXXXX1137 | M952: =TEXT(A952,"dddd") -> Sunday | N952: =DATE(Table4[[#This Row],[year]],Table4[[#This Row],[month2]],Table4[[#This Row],[day]]) -> 46068
A953: =MID(E953,5,2) -> 14 | B953: =_xlfn.SWITCH(Table4[[#This Row],[month]],"jan",1,"feb",2,"mar",3,"apr",4,"may",5,"jun",6,"jul",7,"aug",8,"sep",9,"oct",10,"nov",11,"dec",12,"no month") -> 2 | C953: =LEFT('All Transactions'!$E953,3) -> Feb | D953: =RIGHT(E953,4) -> 2026 | E953: Feb 14, 2026 | F953: 05:03 pm | G953: DEBIT | H953: 710.43 | I953: Paid to Magicpin | J953: T2602141703513065324501 | K953: 528353852359 | L953: Paid by XXXXXXXX1137 | M953: =TEXT(A953,"dddd") -> Saturday | N953: =DATE(Table4[[#This Row],[year]],Table4[[#This Row],[month2]],Table4[[#This Row],[day]]) -> 46067
... A1449: =MID(E1449,5,2) -> 22 | B1449: =_xlfn.SWITCH(Table4[[#This Row],[month]],"jan",1,"feb",2,"mar",3,"apr",4,"may",5,"jun",6,"jul",7,"aug",8,"sep",9,"oct",10,"nov",11,"dec",12,"no month") -> 10 | C1449: =LEFT('All Transactions'!$E1449,3) -> Oct | D1449: =RIGHT(E1449,4) -> 2025 | E1449: Oct 22, 2025 | F1449: 04:46 pm | G1449: DEBIT | H1449: 40 | I1449: Paid to CANE HOUSE PAROTTA & DOSA CENTRE | J1449: T2510221646396234301717 | K1449: 438254951674 | L1449: Paid by XXXXXXXX1137 | M1449: =TEXT(A1449,"dddd") -> Sunday | N1449: =DATE(Table4[[#This Row],[year]],Table4[[#This Row],[month2]],Table4[[#This Row],[day]]) -> 45952
A1450: =MID(E1450,5,2) -> 21 | B1450: =_xlfn.SWITCH(Table4[[#This Row],[month]],"jan",1,"feb",2,"mar",3,"apr",4,"may",5,"jun",6,"jul",7,"aug",8,"sep",9,"oct",10,"nov",11,"dec",12,"no month") -> 10 | C1450: =LEFT('All Transactions'!$E1450,3) -> Oct | D1450: =RIGHT(E1450,4) -> 2025 | E1450: Oct 21, 2025 | F1450: 07:31 pm | G1450: DEBIT | H1450: 2061.8 | I1450: Paid to Narsimha Reddy Engineering College PTM51021805356101229581202510210731 | K1450: 293739242037 | L1450: Paid by XXXXXXXX1137 | M1450: =TEXT(A1450,"dddd") -> Saturday | N1450: =DATE(Table4[[#This Row],[year]],Table4[[#This Row],[month2]],Table4[[#This Row],[day]]) -> 45951
A1451: =MID(E1451,5,2) -> 21 | B1451: =_xlfn.SWITCH(Table4[[#This Row],[month]],"jan",1,"feb",2,"mar",3,"apr",4,"may",5,"jun",6,"jul",7,"aug",8,"sep",9,"oct",10,"nov",11,"dec",12,"no month") -> 10 | C1451: =LEFT('All Transactions'!$E1451,3) -> Oct | D1451: =RIGHT(E1451,4) -> 2025 | E1451: Oct 21, 2025 | F1451: 12:45 pm | G1451: DEBIT | H1451: 10 | I1451: Paid to NRCM Canteen | J1451: T2510211245282855126654 | K1451: 352035957948 | L1451: Paid by XXXX7370 | M1451: =TEXT(A1451,"dddd") -> Saturday | N1451: =DATE(Table4[[#This Row],[year]],Table4[[#This Row],[month2]],Table4[[#This Row],[day]]) -> 45951
A1452: =MID(E1452,5,2) -> 20 | B1452: =_xlfn.SWITCH(Table4[[#This Row],[month]],"jan",1,"feb",2,"mar",3,"apr",4,"may",5,"jun",6,"jul",7,"aug",8,"sep",9,"oct",10,"nov",11,"dec",12,"no month") -> 10 | C1452: =LEFT('All Transactions'!$E1452,3) -> Oct | D1452: =RIGHT(E1452,4) -> 2025 | E1452: Oct 20, 2025 | F1452: 09:44 pm | G1452: DEBIT | H1452: 17 | I1452: Paid to Sai Maruthi Medical And General Stores | J1452: T2510202143561696860584 | K1452: 717370900771 | L1452: Paid by XXXXXXXX1137 | M1452: =TEXT(A1452,"dddd") -> Friday | N1452: =DATE(Table4[[#This Row],[year]],Table4[[#This Row],[month2]],Table4[[#This Row],[day]]) -> 45950
A1453: =MID(E1453,5,2) -> 20 | B1453: =_xlfn.SWITCH(Table4[[#This Row],[month]],"jan",1,"feb",2,"mar",3,"apr",4,"may",5,"jun",6,"jul",7,"aug",8,"sep",9,"oct",10,"nov",11,"dec",12,"no month") -> 10 | C1453: =LEFT('All Transactions'!$E1453,3) -> Oct | D1453: =RIGHT(E1453,4) -> 2025 | E1453: Oct 20, 2025 | F1453: 02:06 pm | G1453: DEBIT | H1453: 100 | I1453: Paid to Pantaiah 01 | J1453: T2510201406156571192382 | K1453: 643550633766 | L1453: Paid by XXXXXXXX1137 | M1453: =TEXT(A1453,"dddd") -> Friday | N1453: =DATE(Table4[[#This Row],[year]],Table4[[#This Row],[month2]],Table4[[#This Row],[day]]) -> 45950
A1454: =MID(E1454,5,2) -> 20 | B1454: =_xlfn.SWITCH(Table4[[#This Row],[month]],"jan",1,"feb",2,"mar",3,"apr",4,"may",5,"jun",6,"jul",7,"aug",8,"sep",9,"oct",10,"nov",11,"dec",12,"no month") -> 10 | C1454: =LEFT('All Transactions'!$E1454,3) -> Oct | D1454: =RIGHT(E1454,4) -> 2025 | E1454: Oct 20, 2025 | F1454: 12:52 pm | G1454: CREDIT | H1454: 1300 | I1454: Received from Babai | J1454: T2510201252444015910112 | K1454: 383698230874 | L1454: Credited to XXXXXXXX1137 | M1454: =TEXT(A1454,"dddd") -> Friday | N1454: =DATE(Table4[[#This Row],[year]],Table4[[#This Row],[month2]],Table4[[#This Row],[day]]) -> 45950
A1455: =MID(E1455,5,2) -> 20 | B1455: =_xlfn.SWITCH(Table4[[#This Row],[month]],"jan",1,"feb",2,"mar",3,"apr",4,"may",5,"jun",6,"jul",7,"aug",8,"sep",9,"oct",10,"nov",11,"dec",12,"no month") -> 10 | C1455: =LEFT('All Transactions'!$E1455,3) -> Oct | D1455: =RIGHT(E1455,4) -> 2025 | E1455: Oct 20, 2025 | F1455: 10:42 am | G1455: DEBIT | H1455: 35 | I1455: Paid to Raju tiffin centre | J1455: T2510201042442484156680 | K1455: 046548139216 | L1455: Paid by XXXXXXXX1137 | M1455: =TEXT(A1455,"dddd") -> Friday | N1455: =DATE(Table4[[#This Row],[year]],Table4[[#This Row],[month2]],Table4[[#This Row],[day]]) -> 45950
A1456: =MID(E1456,5,2) -> 20 | B1456: =_xlfn.SWITCH(Table4[[#This Row],[month]],"jan",1,"feb",2,"mar",3,"apr",4,"may",5,"jun",6,"jul",7,"aug",8,"sep",9,"oct",10,"nov",11,"dec",12,"no month") -> 10 | C1456: =LEFT('All Transactions'!$E1456,3) -> Oct | D1456: =RIGHT(E1456,4) -> 2025 | E1456: Oct 20, 2025 | F1456: 10:08 am | G1456: CREDIT | H1456: 32000 | I1456: Received from Babai | J1456: T2510201008231175089696 | K1456: 553740993710 | L1456: Credited to XXXXXXXX1137 | M1456: =TEXT(A1456,"dddd") -> Friday | N1456: =DATE(Table4[[#This Row],[year]],Table4[[#This Row],[month2]],Table4[[#This Row],[day]]) -> 45950
A1457: =MID(E1457,5,2) -> 19 | B1457: =_xlfn.SWITCH(Table4[[#This Row],[month]],"jan",1,"feb",2,"mar",3,"apr",4,"may",5,"jun",6,"jul",7,"aug",8,"sep",9,"oct",10,"nov",11,"dec",12,"no month") -> 10 | C1457: =LEFT('All Transactions'!$E1457,3) -> Oct | D1457: =RIGHT(E1457,4) -> 2025 | E1457: Oct 19, 2025 | F1457: 07:33 pm | G1457: CREDIT | H1457: 100 | I1457: Received from ******3876 | J1457: T2510191933345166318546 | K1457: 905980928902 | L1457: Credited to XXXXXXXX1137 | M1457: =TEXT(A1457,"dddd") -> Thursday | N1457: =DATE(Table4[[#This Row],[year]],Table4[[#This Row],[month2]],Table4[[#This Row],[day]]) -> 45949
A1458: =MID(E1458,5,2) -> 19 | B1458: =_xlfn.SWITCH(Table4[[#This Row],[month]],"jan",1,"feb",2,"mar",3,"apr",4,"may",5,"jun",6,"jul",7,"aug",8,"sep",9,"oct",10,"nov",11,"dec",12,"no month") -> 10 | C1458: =LEFT('All Transactions'!$E1458,3) -> Oct | D1458: =RIGHT(E1458,4) -> 2025 | E1458: Oct 19, 2025 | F1458: 07:07 pm | G1458: DEBIT | H1458: 107.39 | I1458: Paid to HINDUSTAN PETROLEUM CORPORATION LIMITED | J1458: T2510191907126806350860 | K1458: 144468257215 | L1458: Paid by XXXXXXXX1137 | M1458: =TEXT(A1458,"dddd") -> Thursday | N1458: =DATE(Table4[[#This Row],[year]],Table4[[#This Row],[month2]],Table4[[#This Row],[day]]) -> 45949
...
